Metadata-Version: 1.0
Name: edb-distributions
Version: 0.1
Summary: Module for defining and inspecting Gaussian and Binomial distributions
Home-page: UNKNOWN
Author: UNKNOWN
Author-email: UNKNOWN
License: UNKNOWN
Platform: UNKNOWN
